{
  "name": "profileList",
  "base": "PersistedModel",
  "idInjection": true,
  "options": {
    "validateUpsert": true
  },
  "properties": {
    "name": {
      "type": "string",
      "required": true
    },
    "email": {
      "type": "string"
    },
    "street": {
      "type": "string"
    },
    "city": {
      "type": "string"
    },
    "state": {
      "type": "string"
    },
    "zipcode": {
      "type": "string"
    },
    "phone": {
      "type": "string"
    },
    "allergies": {
      "type": "string"
    },
    "tools": {
      "type": "string"
    },
    "profileId": {
      "type": "string"
    }
  },
  "validations": [],
  "relations": {},
  "acls": [
    {
      "accessType": "EXECUTE",
      "principalType": "ROLE",
      "principalId": "$authenticated",
      "permission": "ALLOW",
      "property": "findOne"
    }
  ],
  "methods": {}
}
